flk/__init__.py
flk/__main__.py
flk/parser.py
flk/variable.py
flk-1.2.5.dist-info/LICENSE
flk-1.2.5.dist-info/METADATA
flk-1.2.5.dist-info/WHEEL
flk-1.2.5.dist-info/top_level.txt
flk-1.2.5.dist-info/RECORD
