Metadata-Version: 2.1
Name: flk
Version: 1.2.5
Summary: FLK - это библиотека для парсинга и работы с файлами в формате FL (File Language).
Home-page: https://github.com/FlacSy/flk
Author: FlacSy
Author-email: flacsy.tw@gmail.com
License: MIT
License-File: LICENSE
